receiver.sv
module receiver #(
	parameter CLOCKS_PER_PULSE = 16
)
(
	input logic clk,
	input logic rstn,
	input logic ready_clr,
	input logic rx,
	output logic ready,
	output logic [7:0] data_out
);

	enum {RX_IDLE, RX_START, RX_DATA, RX_END} state;

	logic[2:0] c_bits = 3'b0;
	logic[$clog2(CLOCKS_PER_PULSE)-1:0] c_clocks = 0;
	
  	logic[7:0] temp_data = 8'b0;
	
	always_ff @(posedge clk or negedge rstn or negedge ready_clr) begin
	
		if (!ready_clr) ready <= 1'b0;
		if (!rstn) begin
			c_clocks <= 0;
			c_bits <= 0;
			//data_out <= 0;
			ready <= 0;
			state <= RX_IDLE;
			
		end else begin 
			case (state)
			RX_IDLE : begin
				if (rx == 0) begin
					state <= RX_START;
					c_clocks <= 0;
				end
			end
			RX_START: begin
				if (c_clocks == CLOCKS_PER_PULSE/2-1) begin
					state <= RX_DATA;
					c_clocks <= 0;
				end else
					c_clocks <= c_clocks + 1;
			end
			RX_DATA : begin
				if (c_clocks == CLOCKS_PER_PULSE-1) begin
					c_clocks <= 0;
					temp_data[c_bits] <= rx;
					if (c_bits == 3'd7) begin
						state <= RX_END;
						c_bits <= 0;
					end else c_bits <= c_bits + 1;
				end else c_clocks <= c_clocks + 1;
			end
			RX_END : begin
				if (c_clocks == CLOCKS_PER_PULSE-1) begin
					//data_out <= temp_data;
					ready <= 1'b1;
					state <= RX_IDLE;
					c_clocks <= 0;
				end else c_clocks <= c_clocks + 1;
			end
			default: state <= RX_IDLE;
			endcase
		end
	end
	assign data_out = temp_data;
endmodule

DE2/transmitter.sv
module transmitter #(
	parameter CLOCKS_PER_PULSE = 16
)
(
	input logic [7:0] data_in,
	input logic data_en,
	input logic clk,
	input logic rstn,
	output logic tx,
	output logic tx_busy
);
	enum {TX_IDLE, TX_START, TX_DATA, TX_END} state;
	
	logic[7:0] data = 8'b0;
	logic[2:0] c_bits = 3'b0;
	logic[$clog2(CLOCKS_PER_PULSE)-1:0] c_clocks = 0;
	
	always_ff @(posedge clk or negedge rstn) begin
		if (!rstn) begin
			c_clocks <= 0;
			c_bits <= 0;
			data <= 0;
          	tx <= 1'b1;
			state <= TX_IDLE;
		end else begin 
			case (state)
			TX_IDLE: begin
				if (~data_en) begin
					state <= TX_START;
					data <= data_in;
					c_bits <= 3'b0;
					c_clocks <= 0;
				end else tx <= 1'b1;
			end
			TX_START: begin
				if (c_clocks == CLOCKS_PER_PULSE-1) begin
					state <= TX_DATA;
					c_clocks <= 0;
				end else begin
					tx <= 1'b0;
					c_clocks <= c_clocks + 1;
				end
			end
			TX_DATA: begin
				if (c_clocks == CLOCKS_PER_PULSE-1) begin
					c_clocks <= 0;
					if (c_bits == 3'd7) begin
						state <= TX_END;
					end else begin
						c_bits <= c_bits + 1;
						tx <= data[c_bits];
					end
				end else begin
					tx <= data[c_bits];
					c_clocks <= c_clocks + 1;
				end
			end
			TX_END: begin
				if (c_clocks == CLOCKS_PER_PULSE-1) begin
					state <= TX_IDLE;
					c_clocks <= 0;
				end else begin
					tx <= 1'b1;
					c_clocks <= c_clocks + 1;
				end
			end
            default: state <= TX_IDLE;
			endcase
		end
	end
	assign tx_busy = (state != TX_IDLE);
	
endmodule

trans_rec_tb.sv
`timescale 1ns/1ps

module trans_rec_tb;
	
	localparam CLOCKS_PER_PULSE = 4; //200_000_000/9600
	
	localparam CLK_PERIOD = 10;
	logic clk=0, rstn=0, data_en=1, tx, tx_busy;
  	logic ready, ready_clr=1;
	
	logic[7:0] data_in = 8'b10101100;
  	logic[7:0] data_out;
	
	always #1 clk <= ~clk;
	
	transmitter #(
      .CLOCKS_PER_PULSE(CLOCKS_PER_PULSE)) trans (.*);
  
    receiver #( 
      .CLOCKS_PER_PULSE(CLOCKS_PER_PULSE)) rec (
      .clk(clk),
      .rstn(rstn),
      .ready_clr(ready_clr),
      .rx(tx),
      .ready(ready),
      .data_out(data_out)
    );
	
	initial begin
		$dumpfile("dump.vcd"); $dumpvars;
		repeat(2) @(posedge clk) #1;
		rstn <= 1;
		data_en <= 0;
		repeat(5) @(posedge clk) #1;
      	data_en <= 1;
      	wait(ready);
      	repeat(10) @(posedge clk) #1;
      	data_in <= 8'b00101011;
      	ready_clr <= 0;
      	#1 data_en <= 0;
      	repeat(5) @(posedge clk) #1;
      	data_en <= 1;
      	ready_clr <= 1;
      	wait(ready);
      	repeat(10) @(posedge clk) #1;
		$finish();
	end
endmodule

simulation/modelsim/dump.vcd
$date
	Mon Jun 12 13:50:40 2023
$end
$version
	ModelSim Version 2020.1
$end
$timescale
	1ps
$end

$scope module trans_rec_tb $end
$var parameter 32 ! CLOCKS_PER_PULSE $end
$var parameter 32 " CLK_PERIOD $end
$var reg 1 # clk $end
$var reg 1 $ rstn $end
$var reg 1 % data_en $end
$var reg 1 & tx $end
$var reg 1 ' tx_busy $end
$var reg 1 ( ready $end
$var reg 1 ) ready_clr $end
$var reg 8 * data_in [7:0] $end
$var reg 8 + data_out [7:0] $end

$scope module trans $end
$var parameter 32 , CLOCKS_PER_PULSE $end
$var wire 1 - data_in [7] $end
$var wire 1 . data_in [6] $end
$var wire 1 / data_in [5] $end
$var wire 1 0 data_in [4] $end
$var wire 1 1 data_in [3] $end
$var wire 1 2 data_in [2] $end
$var wire 1 3 data_in [1] $end
$var wire 1 4 data_in [0] $end
$var wire 1 5 data_en $end
$var wire 1 6 clk $end
$var wire 1 7 rstn $end
$var reg 1 8 tx $end
$var reg 1 9 tx_busy $end
$var integer 32 : state $end
$var reg 8 ; data [7:0] $end
$var reg 3 < c_bits [2:0] $end
$var reg 2 = c_clocks [1:0] $end
$upscope $end

$scope module rec $end
$var parameter 32 > CLOCKS_PER_PULSE $end
$var wire 1 ? clk $end
$var wire 1 @ rstn $end
$var wire 1 A ready_clr $end
$var wire 1 B rx $end
$var reg 1 C ready $end
$var reg 8 D data_out [7:0] $end
$var integer 32 E state $end
$var reg 3 F c_bits [2:0] $end
$var reg 2 G c_clocks [1:0] $end
$var reg 8 H temp_data [7:0] $end
$upscope $end
$upscope $end

$scope begin std $end
$upscope $end
$enddefinitions $end
#0
$dumpvars
0#
0$
1%
1&
0'
0(
1)
b10101100 *
b0 +
18
09
b0 ;
b0 <
b0 =
0C
b0 D
b0 F
b0 G
b0 H
b100 !
b1010 "
b100 ,
b100 >
b0 :
b0 E
04
03
12
11
00
1/
0.
1-
15
06
07
0?
0@
1A
1B
$end
#1000
1#
1?
16
#2000
0#
0?
06
#3000
1#
1?
16
#4000
0#
1$
0%
05
0?
06
1@
17
#5000
1#
1?
16
b1 :
b10101100 ;
19
1'
#6000
0#
0?
06
#7000
1#
1?
16
08
b1 =
0&
0B
#8000
0#
0?
06
#9000
1#
1?
16
b10 =
b1 E
#10000
0#
0?
06
#11000
1#
1?
16
b11 =
b1 G
#12000
0#
0?
06
#13000
1#
1?
16
b10 :
b0 =
b10 E
b0 G
#14000
0#
1%
15
0?
06
#15000
1#
1?
16
b1 =
b1 G
#16000
0#
0?
06
#17000
1#
1?
16
b10 =
b10 G
#18000
0#
0?
06
#19000
1#
1?
16
b11 =
b11 G
#20000
0#
0?
06
#21000
1#
1?
16
b0 =
b1 <
b0 G
b1 F
#22000
0#
0?
06
#23000
1#
1?
16
b1 =
b1 G
#24000
0#
0?
06
#25000
1#
1?
16
b10 =
b10 G
#26000
0#
0?
06
#27000
1#
1?
16
b11 =
b11 G
#28000
0#
0?
06
#29000
1#
1?
16
b0 =
b10 <
b0 G
b10 F
#30000
0#
0?
06
#31000
1#
1?
16
18
b1 =
b1 G
1&
1B
#32000
0#
0?
06
#33000
1#
1?
16
b10 =
b10 G
#34000
0#
0?
06
#35000
1#
1?
16
b11 =
b11 G
#36000
0#
0?
06
#37000
1#
1?
16
b0 =
b11 <
b0 G
b100 H
b11 F
#38000
0#
0?
06
#39000
1#
1?
16
b1 =
b1 G
#40000
0#
0?
06
#41000
1#
1?
16
b10 =
b10 G
#42000
0#
0?
06
#43000
1#
1?
16
b11 =
b11 G
#44000
0#
0?
06
#45000
1#
1?
16
b0 =
b100 <
b0 G
b1100 H
b100 F
#46000
0#
0?
06
#47000
1#
1?
16
08
b1 =
b1 G
0&
0B
#48000
0#
0?
06
#49000
1#
1?
16
b10 =
b10 G
#50000
0#
0?
06
#51000
1#
1?
16
b11 =
b11 G
#52000
0#
0?
06
#53000
1#
1?
16
b0 =
b101 <
b0 G
b101 F
#54000
0#
0?
06
#55000
1#
1?
16
18
b1 =
b1 G
1&
1B
#56000
0#
0?
06
#57000
1#
1?
16
b10 =
b10 G
#58000
0#
0?
06
#59000
1#
1?
16
b11 =
b11 G
#60000
0#
0?
06
#61000
1#
1?
16
b0 =
b110 <
b0 G
b101100 H
b110 F
#62000
0#
0?
06
#63000
1#
1?
16
08
b1 =
b1 G
0&
0B
#64000
0#
0?
06
#65000
1#
1?
16
b10 =
b10 G
#66000
0#
0?
06
#67000
1#
1?
16
b11 =
b11 G
#68000
0#
0?
06
#69000
1#
1?
16
b0 =
b111 <
b0 G
b111 F
#70000
0#
0?
06
#71000
1#
1?
16
18
b1 =
b1 G
1&
1B
#72000
0#
0?
06
#73000
1#
1?
16
b10 =
b10 G
#74000
0#
0?
06
#75000
1#
1?
16
b11 =
b11 G
#76000
0#
0?
06
#77000
1#
1?
16
b0 =
b11 :
b0 G
b10101100 H
b11 E
b0 F
#78000
0#
0?
06
#79000
1#
1?
16
b1 =
b1 G
#80000
0#
0?
06
#81000
1#
1?
16
b10 =
b10 G
#82000
0#
0?
06
#83000
1#
1?
16
b11 =
b11 G
#84000
0#
0?
06
#85000
1#
1?
16
b0 :
b0 =
b10101100 D
1C
b0 E
b0 G
1(
b10101100 +
09
0'
#86000
0#
0?
06
#87000
1#
1?
16
#88000
0#
0?
06
#89000
1#
1?
16
#90000
0#
0?
06
#91000
1#
1?
16
#92000
0#
0?
06
#93000
1#
1?
16
#94000
0#
0?
06
#95000
1#
1?
16
#96000
0#
0?
06
#97000
1#
1?
16
#98000
0#
0?
06
#99000
1#
1?
16
#100000
0#
0?
06
#101000
1#
1?
16
#102000
0#
0?
06
#103000
1#
1?
16
#104000
0#
0?
06
#105000
1#
1?
16
#106000
0#
b101011 *
0)
14
13
02
0-
0?
06
0A
0C
0(
#107000
1#
0%
05
1?
16
b1 :
b101011 ;
b0 <
19
1'
#108000
0#
0?
06
#109000
1#
1?
16
08
b1 =
0&
0B
#110000
0#
0?
06
#111000
1#
1?
16
b10 =
b1 E
#112000
0#
0?
06
#113000
1#
1?
16
b11 =
b1 G
#114000
0#
0?
06
#115000
1#
1?
16
b10 :
b0 =
b10 E
b0 G
#116000
0#
1%
1)
15
0?
06
1A
#117000
1#
1?
16
18
b1 =
b1 G
1&
1B
#118000
0#
0?
06
#119000
1#
1?
16
b10 =
b10 G
#120000
0#
0?
06
#121000
1#
1?
16
b11 =
b11 G
#122000
0#
0?
06
#123000
1#
1?
16
b0 =
b1 <
b0 G
b10101101 H
b1 F
#124000
0#
0?
06
#125000
1#
1?
16
b1 =
b1 G
#126000
0#
0?
06
#127000
1#
1?
16
b10 =
b10 G
#128000
0#
0?
06
#129000
1#
1?
16
b11 =
b11 G
#130000
0#
0?
06
#131000
1#
1?
16
b0 =
b10 <
b0 G
b10101111 H
b10 F
#132000
0#
0?
06
#133000
1#
1?
16
08
b1 =
b1 G
0&
0B
#134000
0#
0?
06
#135000
1#
1?
16
b10 =
b10 G
#136000
0#
0?
06
#137000
1#
1?
16
b11 =
b11 G
#138000
0#
0?
06
#139000
1#
1?
16
b0 =
b11 <
b0 G
b10101011 H
b11 F
#140000
0#
0?
06
#141000
1#
1?
16
18
b1 =
b1 G
1&
1B
#142000
0#
0?
06
#143000
1#
1?
16
b10 =
b10 G
#144000
0#
0?
06
#145000
1#
1?
16
b11 =
b11 G
#146000
0#
0?
06
#147000
1#
1?
16
b0 =
b100 <
b0 G
b100 F
#148000
0#
0?
06
#149000
1#
1?
16
08
b1 =
b1 G
0&
0B
#150000
0#
0?
06
#151000
1#
1?
16
b10 =
b10 G
#152000
0#
0?
06
#153000
1#
1?
16
b11 =
b11 G
#154000
0#
0?
06
#155000
1#
1?
16
b0 =
b101 <
b0 G
b101 F
#156000
0#
0?
06
#157000
1#
1?
16
18
b1 =
b1 G
1&
1B
#158000
0#
0?
06
#159000
1#
1?
16
b10 =
b10 G
#160000
0#
0?
06
#161000
1#
1?
16
b11 =
b11 G
#162000
0#
0?
06
#163000
1#
1?
16
b0 =
b110 <
b0 G
b110 F
#164000
0#
0?
06
#165000
1#
1?
16
08
b1 =
b1 G
0&
0B
#166000
0#
0?
06
#167000
1#
1?
16
b10 =
b10 G
#168000
0#
0?
06
#169000
1#
1?
16
b11 =
b11 G
#170000
0#
0?
06
#171000
1#
1?
16
b0 =
b111 <
b0 G
b111 F
#172000
0#
0?
06
#173000
1#
1?
16
b1 =
b1 G
#174000
0#
0?
06
#175000
1#
1?
16
b10 =
b10 G
#176000
0#
0?
06
#177000
1#
1?
16
b11 =
b11 G
#178000
0#
0?
06
#179000
1#
1?
16
b0 =
b11 :
b0 G
b101011 H
b11 E
b0 F
#180000
0#
0?
06
#181000
1#
1?
16
18
b1 =
b1 G
1&
1B
#182000
0#
0?
06
#183000
1#
1?
16
b10 =
b10 G
#184000
0#
0?
06
#185000
1#
1?
16
b11 =
b11 G
#186000
0#
0?
06
#187000
1#
1?
16
b0 :
b0 =
b101011 D
1C
b0 E
b0 G
1(
b101011 +
09
0'
