binary_to_7seg.sv

module binary_to_7seg ( 
	input logic [3:0] data_in,
	output logic [6:0] data_out
);
    // Make a LUT to convert digits to 7 segment output
    // Input - 4 bits, output - 7 bits
    logic [15:0][6:0] lut_7seg;

    // Output is gfedcba
    assign lut_7seg[0] = 7'b0111111;
    assign lut_7seg[1] = 7'b0000110;
    assign lut_7seg[2] = 7'b1011011;
    assign lut_7seg[3] = 7'b1001111;
    assign lut_7seg[4] = 7'b1100110;
    assign lut_7seg[5] = 7'b1101101;
    assign lut_7seg[6] = 7'b1111101;
    assign lut_7seg[7] = 7'b0000111;
    assign lut_7seg[8] = 7'b1111111;
    assign lut_7seg[9] = 7'b1101111;
    assign lut_7seg[15:10] = 7'b0;    // unused
	 
	 assign data_out = ~lut_7seg[data_in];
	 
endmodule

/*
Seven segment display
    a
f       b
    g
e       c
    d
*/

receiver.sv
module receiver #(
	parameter CLOCKS_PER_PULSE = 16
)
(
	input logic clk,
	input logic rstn,
	input logic ready_clr,
	input logic rx,
	output logic ready,
	output logic [7:0] data_out
);

	enum {RX_IDLE, RX_START, RX_DATA, RX_END} state;

	logic[2:0] c_bits;
	logic[$clog2(CLOCKS_PER_PULSE)-1:0] c_clocks;
	
  	logic[7:0] temp_data;
	logic rx_sync;
	
	always_ff @(posedge clk or negedge rstn) begin
	
		if (!rstn) begin
			c_clocks <= 0;
			c_bits <= 0;
			temp_data <= 8'b0;
			//data_out <= 8'b0;
			ready <= 0;
			state <= RX_IDLE;
			
		end else begin 
			rx_sync <= rx;  // Synchronize the input signal using a flip-flop
			
			case (state)
			RX_IDLE : begin
				if (rx_sync == 0) begin
					state <= RX_START;
					c_clocks <= 0;
				end
			end
			RX_START: begin
				if (c_clocks == CLOCKS_PER_PULSE/2-1) begin
					state <= RX_DATA;
					c_clocks <= 0;
				end else
					c_clocks <= c_clocks + 1;
			end
			RX_DATA : begin
				if (c_clocks == CLOCKS_PER_PULSE-1) begin
					c_clocks <= 0;
					temp_data[c_bits] <= rx_sync;
					if (c_bits == 3'd7) begin
						state <= RX_END;
						c_bits <= 0;
					end else c_bits <= c_bits + 1;
				end else c_clocks <= c_clocks + 1;
			end
			RX_END : begin
				if (c_clocks == CLOCKS_PER_PULSE-1) begin
					//data_out <= temp_data;
					ready <= 1'b1;
					state <= RX_IDLE;
					c_clocks <= 0;
				end else c_clocks <= c_clocks + 1;
			end
			default: state <= RX_IDLE;
			endcase
		end
	end
	assign data_out = temp_data;
endmodule

DE2/transmitter.sv
module transmitter #(
	parameter CLOCKS_PER_PULSE = 16
)
(
	input logic [7:0] data_in,
	input logic data_en,
	input logic clk,
	input logic rstn,
	output logic tx,
	output logic tx_busy
);
	enum {TX_IDLE, TX_START, TX_DATA, TX_END} state;
	
	logic[7:0] data = 8'b0;
	logic[2:0] c_bits = 3'b0;
	logic[$clog2(CLOCKS_PER_PULSE)-1:0] c_clocks = 0;
	
	always_ff @(posedge clk or negedge rstn) begin
		if (!rstn) begin
			c_clocks <= 0;
			c_bits <= 0;
			data <= 0;
          	tx <= 1'b1;
			state <= TX_IDLE;
		end else begin 
			case (state)
			TX_IDLE: begin
				if (~data_en) begin
					state <= TX_START;
					data <= data_in;
					c_bits <= 3'b0;
					c_clocks <= 0;
				end else tx <= 1'b1;
			end
			TX_START: begin
				if (c_clocks == CLOCKS_PER_PULSE-1) begin
					state <= TX_DATA;
					c_clocks <= 0;
				end else begin
					tx <= 1'b0;
					c_clocks <= c_clocks + 1;
				end
			end
			TX_DATA: begin
				if (c_clocks == CLOCKS_PER_PULSE-1) begin
					c_clocks <= 0;
					if (c_bits == 3'd7) begin
						state <= TX_END;
					end else begin
						c_bits <= c_bits + 1;
						tx <= data[c_bits];
					end
				end else begin
					tx <= data[c_bits];
					c_clocks <= c_clocks + 1;
				end
			end
			TX_END: begin
				if (c_clocks == CLOCKS_PER_PULSE-1) begin
					state <= TX_IDLE;
					c_clocks <= 0;
				end else begin
					tx <= 1'b1;
					c_clocks <= c_clocks + 1;
				end
			end
            default: state <= TX_IDLE;
			endcase
		end
	end
	assign tx_busy = (state != TX_IDLE);
	
endmodule

DE2/uart.sv
module uart #(
	parameter CLOCKS_PER_PULSE = 5208
)
(
	input logic [3:0] data_in,
	input logic data_en,
	input logic clk,
	input logic rstn,
	output logic tx,
	output logic tx_busy,
	input logic ready_clr,
	input logic rx,
	output logic ready,
	output logic [3:0] led_out,
	output logic [6:0] display_out
);
	logic [7:0] data_input; 
	logic [7:0] data_output;

	transmitter #(.CLOCKS_PER_PULSE(CLOCKS_PER_PULSE)) uart_tx (
		.data_in(data_input),
		.data_en(data_en),
		.clk(clk),
		.rstn(rstn),
		.tx(tx),
		.tx_busy(tx_busy)
	);
	
	receiver #(.CLOCKS_PER_PULSE(CLOCKS_PER_PULSE)) uart_rx (
		.clk(clk),
		.rstn(rstn),
		.ready_clr(ready_clr),
		.rx(rx),
		.ready(ready),
		.data_out(data_output)
	);
	
	binary_to_7seg converter (
		.data_in(data_output[3:0]),
		.data_out(display_out)
	);
	
	assign data_input = {4'b0, data_in};
	assign led_out = data_output[3:0];
	
	
endmodule

DE2/testbench.sv
`timescale 1ns/1ps

module testbench();

	localparam CLOCKS_PER_PULSE = 4;
  logic [3:0] data_in = 4'b0001;
	logic clk = 0;
	logic rstn = 0;
	logic enable = 1;

	logic tx_busy;
	logic ready;
	logic [3:0] data_out;
	logic [7:0] display_out;

	logic loopback;
	logic ready_clr = 1;

	uart #(.CLOCKS_PER_PULSE(CLOCKS_PER_PULSE)) 
			test_uart(.data_in(data_in),
						.data_en(enable),
						.clk(clk),
						.tx(loopback),
						.tx_busy(tx_busy),
						.rx(loopback),
						.ready(ready),
						.ready_clr(ready_clr),
						.led_out(data_out),
						.display_out(display_out),
						.rstn(rstn)
						);
  
  
	always begin
		#1 clk = ~clk;
	end
  
	initial begin
		$dumpfile("testbench.vcd");
		$dumpvars(0, testbench);
      	rstn <= 1;
		enable <= 1'b0;
      	#2 rstn <= 0;
		#2 rstn <= 1;
		#5 enable <= 1'b1;
	end
      
  	
	always @(posedge ready) begin
	
		if (data_out != data_in) begin
			$display("FAIL: rx data %x does not match tx %x", data_out, data_in);
         $finish();
		end else begin
          if (data_out == 4'b1111) begin //Check if received data is 11111111
				$display("SUCCESS: all bytes verified");
				$finish();
			end
			
			#10 rstn <= 0;
			#2 rstn <= 1;
			data_in <= data_in + 1'b1;
			enable <= 1'b0;
			#2 enable <= 1'b1;
		end
	end
endmodule

simulation/modelsim/testbench.vcd
$date
	Tue Jun 13 01:04:43 2023
$end
$version
	ModelSim Version 2020.1
$end
$timescale
	1ps
$end

$scope module testbench $end
$var parameter 32 ! CLOCKS_PER_PULSE $end
$var reg 4 " data_in [3:0] $end
$var reg 1 # clk $end
$var reg 1 $ rstn $end
$var reg 1 % enable $end
$var reg 1 & tx_busy $end
$var reg 1 ' ready $end
$var reg 4 ( data_out [3:0] $end
$var reg 8 ) display_out [7:0] $end
$var reg 1 * loopback $end
$var reg 1 + ready_clr $end

$scope module test_uart $end
$var parameter 32 , CLOCKS_PER_PULSE $end
$var wire 1 - data_in [3] $end
$var wire 1 . data_in [2] $end
$var wire 1 / data_in [1] $end
$var wire 1 0 data_in [0] $end
$var wire 1 1 data_en $end
$var wire 1 2 clk $end
$var wire 1 3 rstn $end
$var reg 1 4 tx $end
$var reg 1 5 tx_busy $end
$var wire 1 6 ready_clr $end
$var wire 1 7 rx $end
$var reg 1 8 ready $end
$var reg 4 9 led_out [3:0] $end
$var reg 7 : display_out [6:0] $end
$var reg 8 ; data_input [7:0] $end
$var reg 8 < data_output [7:0] $end

$scope module uart_tx $end
$var parameter 32 = CLOCKS_PER_PULSE $end
$var wire 1 > data_in [7] $end
$var wire 1 ? data_in [6] $end
$var wire 1 @ data_in [5] $end
$var wire 1 A data_in [4] $end
$var wire 1 B data_in [3] $end
$var wire 1 C data_in [2] $end
$var wire 1 D data_in [1] $end
$var wire 1 E data_in [0] $end
$var wire 1 1 data_en $end
$var wire 1 2 clk $end
$var wire 1 3 rstn $end
$var reg 1 F tx $end
$var reg 1 G tx_busy $end
$var integer 32 H state $end
$var reg 8 I data [7:0] $end
$var reg 3 J c_bits [2:0] $end
$var reg 2 K c_clocks [1:0] $end
$upscope $end

$scope module uart_rx $end
$var parameter 32 L CLOCKS_PER_PULSE $end
$var wire 1 2 clk $end
$var wire 1 3 rstn $end
$var wire 1 6 ready_clr $end
$var wire 1 7 rx $end
$var reg 1 M ready $end
$var reg 8 N data_out [7:0] $end
$var integer 32 O state $end
$var reg 3 P c_bits [2:0] $end
$var reg 2 Q c_clocks [1:0] $end
$var reg 8 R temp_data [7:0] $end
$var reg 1 S rx_sync $end
$upscope $end

$scope module converter $end
$var wire 1 T data_in [3] $end
$var wire 1 U data_in [2] $end
$var wire 1 V data_in [1] $end
$var wire 1 W data_in [0] $end
$var reg 7 X data_out [6:0] $end
$var reg 112 Y lut_7seg [111:0] $end
$upscope $end
$upscope $end
$upscope $end
$enddefinitions $end
#0
$dumpvars
b1 "
0#
1$
0%
0&
0'
b0 (
b111111 )
1*
1+
14
05
08
b0 9
b111111 :
b1 ;
b0 <
1F
0G
b0 I
b0 J
b0 K
0M
b0 N
b0 P
b0 Q
b0 R
xS
b111111 X
b1101111111111100001111111101110110111001101001111101101100001100111111 Y
b100 !
b100 ,
b100 =
b100 L
b0 H
b0 O
10
0/
0.
0-
01
02
17
16
13
1E
0D
0C
0B
0A
0@
0?
0>
0W
0V
0U
0T
$end
#1000
1#
12
b1 H
b1 I
1S
1G
15
1&
#2000
0#
02
0$
03
b0 I
b0 H
0G
05
0&
#3000
1#
12
#4000
0#
02
1$
13
#5000
1#
12
b1 H
b1 I
1G
15
1&
#6000
0#
02
#7000
1#
12
0F
b1 K
04
0*
07
#8000
0#
02
#9000
1#
12
1%
b10 K
0S
11
#10000
0#
02
#11000
1#
12
b11 K
b1 O
#12000
0#
02
#13000
1#
12
b10 H
b0 K
b1 Q
#14000
0#
02
#15000
1#
12
1F
b1 K
b10 O
b0 Q
14
1*
17
#16000
0#
02
#17000
1#
12
b10 K
1S
b1 Q
#18000
0#
02
#19000
1#
12
b11 K
b10 Q
#20000
0#
02
#21000
1#
12
b0 K
b1 J
b11 Q
#22000
0#
02
#23000
1#
12
0F
b1 K
b0 Q
b1 R
b1 P
b1 N
04
0*
b1 <
b1 9
07
b1 (
1W
b110 X
b110 :
b110 )
#24000
0#
02
#25000
1#
12
b10 K
0S
b1 Q
#26000
0#
02
#27000
1#
12
b11 K
b10 Q
#28000
0#
02
#29000
1#
12
b0 K
b10 J
b11 Q
#30000
0#
02
#31000
1#
12
b1 K
b0 Q
b10 P
#32000
0#
02
#33000
1#
12
b10 K
b1 Q
#34000
0#
02
#35000
1#
12
b11 K
b10 Q
#36000
0#
02
#37000
1#
12
b0 K
b11 J
b11 Q
#38000
0#
02
#39000
1#
12
b1 K
b0 Q
b11 P
#40000
0#
02
#41000
1#
12
b10 K
b1 Q
#42000
0#
02
#43000
1#
12
b11 K
b10 Q
#44000
0#
02
#45000
1#
12
b0 K
b100 J
b11 Q
#46000
0#
02
#47000
1#
12
b1 K
b0 Q
b100 P
#48000
0#
02
#49000
1#
12
b10 K
b1 Q
#50000
0#
02
#51000
1#
12
b11 K
b10 Q
#52000
0#
02
#53000
1#
12
b0 K
b101 J
b11 Q
#54000
0#
02
#55000
1#
12
b1 K
b0 Q
b101 P
#56000
0#
02
#57000
1#
12
b10 K
b1 Q
#58000
0#
02
#59000
1#
12
b11 K
b10 Q
#60000
0#
02
#61000
1#
12
b0 K
b110 J
b11 Q
#62000
0#
02
#63000
1#
12
b1 K
b0 Q
b110 P
#64000
0#
02
#65000
1#
12
b10 K
b1 Q
#66000
0#
02
#67000
1#
12
b11 K
b10 Q
#68000
0#
02
#69000
1#
12
b0 K
b111 J
b11 Q
#70000
0#
02
#71000
1#
12
b1 K
b0 Q
b111 P
#72000
0#
02
#73000
1#
12
b10 K
b1 Q
#74000
0#
02
#75000
1#
12
b11 K
b10 Q
#76000
0#
02
#77000
1#
12
b0 K
b11 H
b11 Q
#78000
0#
02
#79000
1#
12
1F
b1 K
b0 Q
b11 O
b0 P
14
1*
17
#80000
0#
02
#81000
1#
12
b10 K
1S
b1 Q
#82000
0#
02
#83000
1#
12
b11 K
b10 Q
#84000
0#
02
#85000
1#
12
b0 H
b0 K
b11 Q
0G
05
0&
#86000
0#
02
#87000
1#
12
1M
b0 O
b0 Q
18
1'
#88000
0#
02
#89000
1#
12
#90000
0#
02
#91000
1#
12
#92000
0#
02
#93000
1#
12
#94000
0#
02
#95000
1#
12
#96000
0#
02
#97000
1#
12
0$
03
b0 J
b0 I
b0 R
0M
08
b0 N
b0 <
0'
b0 9
b0 (
0W
b111111 X
b111111 :
b111111 )
#98000
0#
02
#99000
1#
12
1$
b10 "
0%
00
1/
01
b10 ;
0E
1D
13
#100000
0#
02
#101000
1#
12
1%
b1 H
b10 I
1G
11
15
1&
#102000
0#
02
#103000
1#
12
0F
b1 K
04
0*
07
#104000
0#
02
#105000
1#
12
b10 K
0S
#106000
0#
02
#107000
1#
12
b11 K
b1 O
#108000
0#
02
#109000
1#
12
b10 H
b0 K
b1 Q
#110000
0#
02
#111000
1#
12
b1 K
b10 O
b0 Q
#112000
0#
02
#113000
1#
12
b10 K
b1 Q
#114000
0#
02
#115000
1#
12
b11 K
b10 Q
#116000
0#
02
#117000
1#
12
b0 K
b1 J
b11 Q
#118000
0#
02
#119000
1#
12
1F
b1 K
b0 Q
b1 P
14
1*
17
#120000
0#
02
#121000
1#
12
b10 K
1S
b1 Q
#122000
0#
02
#123000
1#
12
b11 K
b10 Q
#124000
0#
02
#125000
1#
12
b0 K
b10 J
b11 Q
#126000
0#
02
#127000
1#
12
0F
b1 K
b0 Q
b10 R
b10 P
b10 N
04
0*
b10 <
b10 9
07
b10 (
1V
b1011011 X
b1011011 :
b1011011 )
#128000
0#
02
#129000
1#
12
b10 K
0S
b1 Q
#130000
0#
02
#131000
1#
12
b11 K
b10 Q
#132000
0#
02
#133000
1#
12
b0 K
b11 J
b11 Q
#134000
0#
02
#135000
1#
12
b1 K
b0 Q
b11 P
#136000
0#
02
#137000
1#
12
b10 K
b1 Q
#138000
0#
02
#139000
1#
12
b11 K
b10 Q
#140000
0#
02
#141000
1#
12
b0 K
b100 J
b11 Q
#142000
0#
02
#143000
1#
12
b1 K
b0 Q
b100 P
#144000
0#
02
#145000
1#
12
b10 K
b1 Q
#146000
0#
02
#147000
1#
12
b11 K
b10 Q
#148000
0#
02
#149000
1#
12
b0 K
b101 J
b11 Q
#150000
0#
02
#151000
1#
12
b1 K
b0 Q
b101 P
#152000
0#
02
#153000
1#
12
b10 K
b1 Q
#154000
0#
02
#155000
1#
12
b11 K
b10 Q
#156000
0#
02
#157000
1#
12
b0 K
b110 J
b11 Q
#158000
0#
02
#159000
1#
12
b1 K
b0 Q
b110 P
#160000
0#
02
#161000
1#
12
b10 K
b1 Q
#162000
0#
02
#163000
1#
12
b11 K
b10 Q
#164000
0#
02
#165000
1#
12
b0 K
b111 J
b11 Q
#166000
0#
02
#167000
1#
12
b1 K
b0 Q
b111 P
#168000
0#
02
#169000
1#
12
b10 K
b1 Q
#170000
0#
02
#171000
1#
12
b11 K
b10 Q
#172000
0#
02
#173000
1#
12
b0 K
b11 H
b11 Q
#174000
0#
02
#175000
1#
12
1F
b1 K
b0 Q
b11 O
b0 P
14
1*
17
#176000
0#
02
#177000
1#
12
b10 K
1S
b1 Q
#178000
0#
02
#179000
1#
12
b11 K
b10 Q
#180000
0#
02
#181000
1#
12
b0 H
b0 K
b11 Q
0G
05
0&
#182000
0#
02
#183000
1#
12
1M
b0 O
b0 Q
18
1'
#184000
0#
02
#185000
1#
12
#186000
0#
02
#187000
1#
12
#188000
0#
02
#189000
1#
12
#190000
0#
02
#191000
1#
12
#192000
0#
02
#193000
1#
12
0$
03
b0 J
b0 I
b0 R
0M
08
b0 N
b0 <
0'
b0 9
b0 (
0V
b111111 X
b111111 :
b111111 )
#194000
0#
02
#195000
1#
12
1$
b11 "
0%
10
01
b11 ;
1E
13
#196000
0#
02
#197000
1#
12
1%
b1 H
b11 I
1G
11
15
1&
#198000
0#
02
#199000
1#
12
0F
b1 K
04
0*
07
#200000
0#
02
#201000
1#
12
b10 K
0S
#202000
0#
02
#203000
1#
12
b11 K
b1 O
#204000
0#
02
#205000
1#
12
b10 H
b0 K
b1 Q
#206000
0#
02
#207000
1#
12
1F
b1 K
b10 O
b0 Q
14
1*
17
#208000
0#
02
#209000
1#
12
b10 K
1S
b1 Q
#210000
0#
02
#211000
1#
12
b11 K
b10 Q
#212000
0#
02
#213000
1#
12
b0 K
b1 J
b11 Q
#214000
0#
02
#215000
1#
12
b1 K
b0 Q
b1 R
b1 P
b1 N
b1 <
b1 9
b1 (
1W
b110 X
b110 :
b110 )
#216000
0#
02
#217000
1#
12
b10 K
b1 Q
#218000
0#
02
#219000
1#
12
b11 K
b10 Q
#220000
0#
02
#221000
1#
12
b0 K
b10 J
b11 Q
#222000
0#
02
#223000
1#
12
0F
b1 K
b0 Q
b11 R
b10 P
b11 N
04
0*
b11 <
b11 9
07
b11 (
1V
b1001111 X
b1001111 :
b1001111 )
#224000
0#
02
#225000
1#
12
b10 K
0S
b1 Q
#226000
0#
02
#227000
1#
12
b11 K
b10 Q
#228000
0#
02
#229000
1#
12
b0 K
b11 J
b11 Q
#230000
0#
02
#231000
1#
12
b1 K
b0 Q
b11 P
#232000
0#
02
#233000
1#
12
b10 K
b1 Q
#234000
0#
02
#235000
1#
12
b11 K
b10 Q
#236000
0#
02
#237000
1#
12
b0 K
b100 J
b11 Q
#238000
0#
02
#239000
1#
12
b1 K
b0 Q
b100 P
#240000
0#
02
#241000
1#
12
b10 K
b1 Q
#242000
0#
02
#243000
1#
12
b11 K
b10 Q
#244000
0#
02
#245000
1#
12
b0 K
b101 J
b11 Q
#246000
0#
02
#247000
1#
12
b1 K
b0 Q
b101 P
#248000
0#
02
#249000
1#
12
b10 K
b1 Q
#250000
0#
02
#251000
1#
12
b11 K
b10 Q
#252000
0#
02
#253000
1#
12
b0 K
b110 J
b11 Q
#254000
0#
02
#255000
1#
12
b1 K
b0 Q
b110 P
#256000
0#
02
#257000
1#
12
b10 K
b1 Q
#258000
0#
02
#259000
1#
12
b11 K
b10 Q
#260000
0#
02
#261000
1#
12
b0 K
b111 J
b11 Q
#262000
0#
02
#263000
1#
12
b1 K
b0 Q
b111 P
#264000
0#
02
#265000
1#
12
b10 K
b1 Q
#266000
0#
02
#267000
1#
12
b11 K
b10 Q
#268000
0#
02
#269000
1#
12
b0 K
b11 H
b11 Q
#270000
0#
02
#271000
1#
12
1F
b1 K
b0 Q
b11 O
b0 P
14
1*
17
#272000
0#
02
#273000
1#
12
b10 K
1S
b1 Q
#274000
0#
02
#275000
1#
12
b11 K
b10 Q
#276000
0#
02
#277000
1#
12
b0 H
b0 K
b11 Q
0G
05
0&
#278000
0#
02
#279000
1#
12
1M
b0 O
b0 Q
18
1'
#280000
0#
02
#281000
1#
12
#282000
0#
02
#283000
1#
12
#284000
0#
02
#285000
1#
12
#286000
0#
02
#287000
1#
12
#288000
0#
02
#289000
1#
12
0$
03
b0 J
b0 I
b0 R
0M
08
b0 N
b0 <
0'
b0 9
b0 (
0W
0V
b111111 X
b111111 :
b111111 )
#290000
0#
02
#291000
1#
12
1$
b100 "
0%
00
0/
1.
01
b100 ;
0E
0D
1C
13
#292000
0#
02
#293000
1#
12
1%
b1 H
b100 I
1G
11
15
1&
#294000
0#
02
#295000
1#
12
0F
b1 K
04
0*
07
#296000
0#
02
#297000
1#
12
b10 K
0S
#298000
0#
02
#299000
1#
12
b11 K
b1 O
#300000
0#
02
#301000
1#
12
b10 H
b0 K
b1 Q
#302000
0#
02
#303000
1#
12
b1 K
b10 O
b0 Q
#304000
0#
02
#305000
1#
12
b10 K
b1 Q
#306000
0#
02
#307000
1#
12
b11 K
b10 Q
#308000
0#
02
#309000
1#
12
b0 K
b1 J
b11 Q
#310000
0#
02
#311000
1#
12
b1 K
b0 Q
b1 P
#312000
0#
02
#313000
1#
12
b10 K
b1 Q
#314000
0#
02
#315000
1#
12
b11 K
b10 Q
#316000
0#
02
#317000
1#
12
b0 K
b10 J
b11 Q
#318000
0#
02
#319000
1#
12
1F
b1 K
b0 Q
b10 P
14
1*
17
#320000
0#
02
#321000
1#
12
b10 K
1S
b1 Q
#322000
0#
02
#323000
1#
12
b11 K
b10 Q
#324000
0#
02
#325000
1#
12
b0 K
b11 J
b11 Q
#326000
0#
02
#327000
1#
12
0F
b1 K
b0 Q
b100 R
b11 P
b100 N
04
0*
b100 <
b100 9
07
b100 (
1U
b1100110 X
b1100110 :
b1100110 )
#328000
0#
02
#329000
1#
12
b10 K
0S
b1 Q
#330000
0#
02
#331000
1#
12
b11 K
b10 Q
#332000
0#
02
#333000
1#
12
b0 K
b100 J
b11 Q
#334000
0#
02
#335000
1#
12
b1 K
b0 Q
b100 P
#336000
0#
02
#337000
1#
12
b10 K
b1 Q
#338000
0#
02
#339000
1#
12
b11 K
b10 Q
#340000
0#
02
#341000
1#
12
b0 K
b101 J
b11 Q
#342000
0#
02
#343000
1#
12
b1 K
b0 Q
b101 P
#344000
0#
02
#345000
1#
12
b10 K
b1 Q
#346000
0#
02
#347000
1#
12
b11 K
b10 Q
#348000
0#
02
#349000
1#
12
b0 K
b110 J
b11 Q
#350000
0#
02
#351000
1#
12
b1 K
b0 Q
b110 P
#352000
0#
02
#353000
1#
12
b10 K
b1 Q
#354000
0#
02
#355000
1#
12
b11 K
b10 Q
#356000
0#
02
#357000
1#
12
b0 K
b111 J
b11 Q
#358000
0#
02
#359000
1#
12
b1 K
b0 Q
b111 P
#360000
0#
02
#361000
1#
12
b10 K
b1 Q
#362000
0#
02
#363000
1#
12
b11 K
b10 Q
#364000
0#
02
#365000
1#
12
b0 K
b11 H
b11 Q
#366000
0#
02
#367000
1#
12
1F
b1 K
b0 Q
b11 O
b0 P
14
1*
17
#368000
0#
02
#369000
1#
12
b10 K
1S
b1 Q
#370000
0#
02
#371000
1#
12
b11 K
b10 Q
#372000
0#
02
#373000
1#
12
b0 H
b0 K
b11 Q
0G
05
0&
#374000
0#
02
#375000
1#
12
1M
b0 O
b0 Q
18
1'
#376000
0#
02
#377000
1#
12
#378000
0#
02
#379000
1#
12
#380000
0#
02
#381000
1#
12
#382000
0#
02
#383000
1#
12
#384000
0#
02
#385000
1#
12
0$
03
b0 J
b0 I
b0 R
0M
08
b0 N
b0 <
0'
b0 9
b0 (
0U
b111111 X
b111111 :
b111111 )
#386000
0#
02
#387000
1#
12
1$
b101 "
0%
10
01
b101 ;
1E
13
#388000
0#
02
#389000
1#
12
1%
b1 H
b101 I
1G
11
15
1&
#390000
0#
02
#391000
1#
12
0F
b1 K
04
0*
07
#392000
0#
02
#393000
1#
12
b10 K
0S
#394000
0#
02
#395000
1#
12
b11 K
b1 O
#396000
0#
02
#397000
1#
12
b10 H
b0 K
b1 Q
#398000
0#
02
#399000
1#
12
1F
b1 K
b10 O
b0 Q
14
1*
17
#400000
0#
02
#401000
1#
12
b10 K
1S
b1 Q
#402000
0#
02
#403000
1#
12
b11 K
b10 Q
#404000
0#
02
#405000
1#
12
b0 K
b1 J
b11 Q
#406000
0#
02
#407000
1#
12
0F
b1 K
b0 Q
b1 R
b1 P
b1 N
04
0*
b1 <
b1 9
07
b1 (
1W
b110 X
b110 :
b110 )
#408000
0#
02
#409000
1#
12
b10 K
0S
b1 Q
#410000
0#
02
#411000
1#
12
b11 K
b10 Q
#412000
0#
02
#413000
1#
12
b0 K
b10 J
b11 Q
#414000
0#
02
#415000
1#
12
1F
b1 K
b0 Q
b10 P
14
1*
17
#416000
0#
02
#417000
1#
12
b10 K
1S
b1 Q
#418000
0#
02
#419000
1#
12
b11 K
b10 Q
#420000
0#
02
#421000
1#
12
b0 K
b11 J
b11 Q
#422000
0#
02
#423000
1#
12
0F
b1 K
b0 Q
b101 R
b11 P
b101 N
04
0*
b101 <
b101 9
07
b101 (
1U
b1101101 X
b1101101 :
b1101101 )
#424000
0#
02
#425000
1#
12
b10 K
0S
b1 Q
#426000
0#
02
#427000
1#
12
b11 K
b10 Q
#428000
0#
02
#429000
1#
12
b0 K
b100 J
b11 Q
#430000
0#
02
#431000
1#
12
b1 K
b0 Q
b100 P
#432000
0#
02
#433000
1#
12
b10 K
b1 Q
#434000
0#
02
#435000
1#
12
b11 K
b10 Q
#436000
0#
02
#437000
1#
12
b0 K
b101 J
b11 Q
#438000
0#
02
#439000
1#
12
b1 K
b0 Q
b101 P
#440000
0#
02
#441000
1#
12
b10 K
b1 Q
#442000
0#
02
#443000
1#
12
b11 K
b10 Q
#444000
0#
02
#445000
1#
12
b0 K
b110 J
b11 Q
#446000
0#
02
#447000
1#
12
b1 K
b0 Q
b110 P
#448000
0#
02
#449000
1#
12
b10 K
b1 Q
#450000
0#
02
#451000
1#
12
b11 K
b10 Q
#452000
0#
02
#453000
1#
12
b0 K
b111 J
b11 Q
#454000
0#
02
#455000
1#
12
b1 K
b0 Q
b111 P
#456000
0#
02
#457000
1#
12
b10 K
b1 Q
#458000
0#
02
#459000
1#
12
b11 K
b10 Q
#460000
0#
02
#461000
1#
12
b0 K
b11 H
b11 Q
#462000
0#
02
#463000
1#
12
1F
b1 K
b0 Q
b11 O
b0 P
14
1*
17
#464000
0#
02
#465000
1#
12
b10 K
1S
b1 Q
#466000
0#
02
#467000
1#
12
b11 K
b10 Q
#468000
0#
02
#469000
1#
12
b0 H
b0 K
b11 Q
0G
05
0&
#470000
0#
02
#471000
1#
12
1M
b0 O
b0 Q
18
1'
#472000
0#
02
#473000
1#
12
#474000
0#
02
#475000
1#
12
#476000
0#
02
#477000
1#
12
#478000
0#
02
#479000
1#
12
#480000
0#
02
#481000
1#
12
0$
03
b0 J
b0 I
b0 R
0M
08
b0 N
b0 <
0'
b0 9
b0 (
0W
0U
b111111 X
b111111 :
b111111 )
#482000
0#
02
#483000
1#
12
1$
b110 "
0%
00
1/
01
b110 ;
0E
1D
13
#484000
0#
02
#485000
1#
12
1%
b1 H
b110 I
1G
11
15
1&
#486000
0#
02
#487000
1#
12
0F
b1 K
04
0*
07
#488000
0#
02
#489000
1#
12
b10 K
0S
#490000
0#
02
#491000
1#
12
b11 K
b1 O
#492000
0#
02
#493000
1#
12
b10 H
b0 K
b1 Q
#494000
0#
02
#495000
1#
12
b1 K
b10 O
b0 Q
#496000
0#
02
#497000
1#
12
b10 K
b1 Q
#498000
0#
02
#499000
1#
12
b11 K
b10 Q
#500000
0#
02
#501000
1#
12
b0 K
b1 J
b11 Q
#502000
0#
02
#503000
1#
12
1F
b1 K
b0 Q
b1 P
14
1*
17
#504000
0#
02
#505000
1#
12
b10 K
1S
b1 Q
#506000
0#
02
#507000
1#
12
b11 K
b10 Q
#508000
0#
02
#509000
1#
12
b0 K
b10 J
b11 Q
#510000
0#
02
#511000
1#
12
b1 K
b0 Q
b10 R
b10 P
b10 N
b10 <
b10 9
b10 (
1V
b1011011 X
b1011011 :
b1011011 )
#512000
0#
02
#513000
1#
12
b10 K
b1 Q
#514000
0#
02
#515000
1#
12
b11 K
b10 Q
#516000
0#
02
#517000
1#
12
b0 K
b11 J
b11 Q
#518000
0#
02
#519000
1#
12
0F
b1 K
b0 Q
b110 R
b11 P
b110 N
04
0*
b110 <
b110 9
07
b110 (
1U
b1111101 X
b1111101 :
b1111101 )
#520000
0#
02
#521000
1#
12
b10 K
0S
b1 Q
#522000
0#
02
#523000
1#
12
b11 K
b10 Q
#524000
0#
02
#525000
1#
12
b0 K
b100 J
b11 Q
#526000
0#
02
#527000
1#
12
b1 K
b0 Q
b100 P
#528000
0#
02
#529000
1#
12
b10 K
b1 Q
#530000
0#
02
#531000
1#
12
b11 K
b10 Q
#532000
0#
02
#533000
1#
12
b0 K
b101 J
b11 Q
#534000
0#
02
#535000
1#
12
b1 K
b0 Q
b101 P
#536000
0#
02
#537000
1#
12
b10 K
b1 Q
#538000
0#
02
#539000
1#
12
b11 K
b10 Q
#540000
0#
02
#541000
1#
12
b0 K
b110 J
b11 Q
#542000
0#
02
#543000
1#
12
b1 K
b0 Q
b110 P
#544000
0#
02
#545000
1#
12
b10 K
b1 Q
#546000
0#
02
#547000
1#
12
b11 K
b10 Q
#548000
0#
02
#549000
1#
12
b0 K
b111 J
b11 Q
#550000
0#
02
#551000
1#
12
b1 K
b0 Q
b111 P
#552000
0#
02
#553000
1#
12
b10 K
b1 Q
#554000
0#
02
#555000
1#
12
b11 K
b10 Q
#556000
0#
02
#557000
1#
12
b0 K
b11 H
b11 Q
#558000
0#
02
#559000
1#
12
1F
b1 K
b0 Q
b11 O
b0 P
14
1*
17
#560000
0#
02
#561000
1#
12
b10 K
1S
b1 Q
#562000
0#
02
#563000
1#
12
b11 K
b10 Q
#564000
0#
02
#565000
1#
12
b0 H
b0 K
b11 Q
0G
05
0&
#566000
0#
02
#567000
1#
12
1M
b0 O
b0 Q
18
1'
#568000
0#
02
#569000
1#
12
#570000
0#
02
#571000
1#
12
#572000
0#
02
#573000
1#
12
#574000
0#
02
#575000
1#
12
#576000
0#
02
#577000
1#
12
0$
03
b0 J
b0 I
b0 R
0M
08
b0 N
b0 <
0'
b0 9
b0 (
0V
0U
b111111 X
b111111 :
b111111 )
#578000
0#
02
#579000
1#
12
1$
b111 "
0%
10
01
b111 ;
1E
13
#580000
0#
02
#581000
1#
12
1%
b1 H
b111 I
1G
11
15
1&
#582000
0#
02
#583000
1#
12
0F
b1 K
04
0*
07
#584000
0#
02
#585000
1#
12
b10 K
0S
#586000
0#
02
