receiver.sv
module receiver #(
	parameter CLOCKS_PER_PULSE = 16
)
(
	input logic clk,
	input logic rstn,
	input logic ready_clr,
	input logic rx,
	output logic ready,
	output logic [7:0] data_out
);

	enum {RX_IDLE, RX_START, RX_DATA, RX_END} state;

	logic[2:0] c_bits;
	logic[$clog2(CLOCKS_PER_PULSE)-1:0] c_clocks;
	
  	logic[7:0] temp_data;
	logic rx_sync;
	
	always_ff @(posedge clk or negedge rstn) begin
	
		if (!rstn) begin
			c_clocks <= 0;
			c_bits <= 0;
			temp_data <= 8'b0;
			//data_out <= 8'b0;
			ready <= 0;
			state <= RX_IDLE;
			
		end else begin 
			rx_sync <= rx;  // Synchronize the input signal using a flip-flop
			
			case (state)
			RX_IDLE : begin
				if (rx_sync == 0) begin
					state <= RX_START;
					c_clocks <= 0;
				end
			end
			RX_START: begin
				if (c_clocks == CLOCKS_PER_PULSE/2-1) begin
					state <= RX_DATA;
					c_clocks <= 0;
				end else
					c_clocks <= c_clocks + 1;
			end
			RX_DATA : begin
				if (c_clocks == CLOCKS_PER_PULSE-1) begin
					c_clocks <= 0;
					temp_data[c_bits] <= rx_sync;
					if (c_bits == 3'd7) begin
						state <= RX_END;
						c_bits <= 0;
					end else c_bits <= c_bits + 1;
				end else c_clocks <= c_clocks + 1;
			end
			RX_END : begin
				if (c_clocks == CLOCKS_PER_PULSE-1) begin
					//data_out <= temp_data;
					ready <= 1'b1;
					state <= RX_IDLE;
					c_clocks <= 0;
				end else c_clocks <= c_clocks + 1;
			end
			default: state <= RX_IDLE;
			endcase
		end
	end
	assign data_out = temp_data;
endmodule

DE2/transmitter.sv
module transmitter #(
	parameter CLOCKS_PER_PULSE = 16
)
(
	input logic [7:0] data_in,
	input logic data_en,
	input logic clk,
	input logic rstn,
	output logic tx,
	output logic tx_busy
);
	enum {TX_IDLE, TX_START, TX_DATA, TX_END} state;
	
	logic[7:0] data = 8'b0;
	logic[2:0] c_bits = 3'b0;
	logic[$clog2(CLOCKS_PER_PULSE)-1:0] c_clocks = 0;
	
	always_ff @(posedge clk or negedge rstn) begin
		if (!rstn) begin
			c_clocks <= 0;
			c_bits <= 0;
			data <= 0;
          	tx <= 1'b1;
			state <= TX_IDLE;
		end else begin 
			case (state)
			TX_IDLE: begin
				if (~data_en) begin
					state <= TX_START;
					data <= data_in;
					c_bits <= 3'b0;
					c_clocks <= 0;
				end else tx <= 1'b1;
			end
			TX_START: begin
				if (c_clocks == CLOCKS_PER_PULSE-1) begin
					state <= TX_DATA;
					c_clocks <= 0;
				end else begin
					tx <= 1'b0;
					c_clocks <= c_clocks + 1;
				end
			end
			TX_DATA: begin
				if (c_clocks == CLOCKS_PER_PULSE-1) begin
					c_clocks <= 0;
					if (c_bits == 3'd7) begin
						state <= TX_END;
					end else begin
						c_bits <= c_bits + 1;
						tx <= data[c_bits];
					end
				end else begin
					tx <= data[c_bits];
					c_clocks <= c_clocks + 1;
				end
			end
			TX_END: begin
				if (c_clocks == CLOCKS_PER_PULSE-1) begin
					state <= TX_IDLE;
					c_clocks <= 0;
				end else begin
					tx <= 1'b1;
					c_clocks <= c_clocks + 1;
				end
			end
            default: state <= TX_IDLE;
			endcase
		end
	end
	assign tx_busy = (state != TX_IDLE);
	
endmodule

uart.sv
module uart #(
	parameter CLOCKS_PER_PULSE = 16
)
(
	input logic [3:0] data_in,
	input logic data_en,
	input logic clk,
	input logic rstn,
	output logic tx,
	output logic tx_busy,
	input logic ready_clr,
	input logic rx,
	output logic ready,
	output logic [3:0] data_out
);
	logic [7:0] data_input; 
	logic [7:0] data_output;

	transmitter #(.CLOCKS_PER_PULSE(CLOCKS_PER_PULSE)) uart_tx (
		.data_in(data_input),
		.data_en(data_en),
		.clk(clk),
		.rstn(rstn),
		.tx(tx),
		.tx_busy(tx_busy)
	);
	
	receiver #(.CLOCKS_PER_PULSE(CLOCKS_PER_PULSE)) uart_rx (
		.clk(clk),
		.rstn(rstn),
		.ready_clr(ready_clr),
		.rx(rx),
		.ready(ready),
		.data_out(data_output)
	);
	
	assign data_input = {4'b0, data_in};
	assign data_out = data_output[3:0];
	
endmodule

testbench.sv
`timescale 1ns/1ps

module testbench();

	localparam CLOCKS_PER_PULSE = 4;
  logic [3:0] data_in = 4'b001;
	logic clk = 0;
	logic rstn = 0;
	logic enable = 1;

	logic tx_busy;
	logic ready;
	logic [7:0] data_out;

	logic loopback;
	logic ready_clr = 1;

	uart #(.CLOCKS_PER_PULSE(CLOCKS_PER_PULSE)) 
			test_uart(.data_in(data_in),
						.data_en(enable),
						.clk(clk),
						.tx(loopback),
						.tx_busy(tx_busy),
						.rx(loopback),
						.ready(ready),
						.ready_clr(ready_clr),
						.data_out(data_out),
						.rstn(rstn)
						);
  
  
	always begin
		#1 clk = ~clk;
	end
  
	initial begin
		$dumpfile("testbench.vcd");
		$dumpvars(0, testbench);
      	rstn <= 1;
		enable <= 1'b0;
      	#2 ready_clr <= 0;
		#5 enable <= 1'b1;
		#2 ready_clr <= 1;
	end
      
  	
	always @(posedge ready) begin
		#2 ready_clr <= 0;
		#2 ready_clr <= 1;
		if (data_out != data_in) begin
			$display("FAIL: rx data %x does not match tx %x", data_out, data_in);
          $finish();
		end 
		else begin
          if (data_out == 4'b1111) begin //Check if received data is 11111111
				$display("SUCCESS: all bytes verified");
				$finish();
			end
			data_in <= data_in + 1'b1;
			enable <= 1'b0;
			#2 enable <= 1'b1;
		end
	end
endmodule

simulation/modelsim/testbench.vcd
$date
	Mon Jun 12 23:57:27 2023
$end
$version
	ModelSim Version 2020.1
$end
$timescale
	1ps
$end

$scope module testbench $end
$var parameter 32 ! CLOCKS_PER_PULSE $end
$var reg 4 " data_in [3:0] $end
$var reg 1 # clk $end
$var reg 1 $ rstn $end
$var reg 1 % enable $end
$var reg 1 & tx_busy $end
$var reg 1 ' ready $end
$var reg 8 ( data_out [7:0] $end
$var reg 1 ) loopback $end
$var reg 1 * ready_clr $end

$scope module test_uart $end
$var parameter 32 + CLOCKS_PER_PULSE $end
$var wire 1 , data_in [3] $end
$var wire 1 - data_in [2] $end
$var wire 1 . data_in [1] $end
$var wire 1 / data_in [0] $end
$var wire 1 0 data_en $end
$var wire 1 1 clk $end
$var wire 1 2 rstn $end
$var reg 1 3 tx $end
$var reg 1 4 tx_busy $end
$var wire 1 5 ready_clr $end
$var wire 1 6 rx $end
$var reg 1 7 ready $end
$var reg 4 8 data_out [3:0] $end
$var reg 8 9 data_input [7:0] $end
$var reg 8 : data_output [7:0] $end

$scope module uart_tx $end
$var parameter 32 ; CLOCKS_PER_PULSE $end
$var wire 1 < data_in [7] $end
$var wire 1 = data_in [6] $end
$var wire 1 > data_in [5] $end
$var wire 1 ? data_in [4] $end
$var wire 1 @ data_in [3] $end
$var wire 1 A data_in [2] $end
$var wire 1 B data_in [1] $end
$var wire 1 C data_in [0] $end
$var wire 1 0 data_en $end
$var wire 1 1 clk $end
$var wire 1 2 rstn $end
$var reg 1 D tx $end
$var reg 1 E tx_busy $end
$var integer 32 F state $end
$var reg 8 G data [7:0] $end
$var reg 3 H c_bits [2:0] $end
$var reg 2 I c_clocks [1:0] $end
$upscope $end

$scope module uart_rx $end
$var parameter 32 J CLOCKS_PER_PULSE $end
$var wire 1 1 clk $end
$var wire 1 2 rstn $end
$var wire 1 5 ready_clr $end
$var wire 1 6 rx $end
$var reg 1 K ready $end
$var reg 8 L data_out [7:0] $end
$var integer 32 M state $end
$var reg 3 N c_bits [2:0] $end
$var reg 2 O c_clocks [1:0] $end
$var reg 8 P temp_data [7:0] $end
$var reg 1 Q rx_sync $end
$upscope $end
$upscope $end
$upscope $end
$enddefinitions $end
#0
$dumpvars
b1 "
0#
1$
0%
0&
0'
b0 (
1)
1*
13
04
07
b0 8
b1 9
b0 :
1D
0E
b0 G
b0 H
b0 I
0K
b0 L
b0 N
b0 O
b0 P
xQ
b100 !
b100 +
b100 ;
b100 J
b0 F
b0 M
1/
0.
0-
0,
00
01
16
15
12
1C
0B
0A
0@
0?
0>
0=
0<
$end
#1000
1#
11
b1 F
b1 G
1Q
1E
14
1&
#2000
0#
01
0$
02
b0 G
b0 F
0E
04
0&
#3000
1#
11
#4000
0#
01
1$
12
#5000
1#
11
b1 F
b1 G
1E
14
1&
#6000
0#
01
#7000
1#
11
0D
b1 I
03
0)
06
#8000
0#
01
#9000
1#
11
1%
b10 I
0Q
10
#10000
0#
01
#11000
1#
11
b11 I
b1 M
#12000
0#
01
#13000
1#
11
b10 F
b0 I
b1 O
#14000
0#
01
#15000
1#
11
1D
b1 I
b10 M
b0 O
13
1)
16
#16000
0#
01
#17000
1#
11
b10 I
1Q
b1 O
#18000
0#
01
#19000
1#
11
b11 I
b10 O
#20000
0#
01
#21000
1#
11
b0 I
b1 H
b11 O
#22000
0#
01
#23000
1#
11
0D
b1 I
b0 O
b1 P
b1 N
b1 L
03
0)
b1 :
b1 8
06
b1 (
#24000
0#
01
#25000
1#
11
b10 I
0Q
b1 O
#26000
0#
01
#27000
1#
11
b11 I
b10 O
#28000
0#
01
#29000
1#
11
b0 I
b10 H
b11 O
#30000
0#
01
#31000
1#
11
b1 I
b0 O
b10 N
#32000
0#
01
#33000
1#
11
b10 I
b1 O
#34000
0#
01
#35000
1#
11
b11 I
b10 O
#36000
0#
01
#37000
1#
11
b0 I
b11 H
b11 O
#38000
0#
01
#39000
1#
11
b1 I
b0 O
b11 N
#40000
0#
01
#41000
1#
11
b10 I
b1 O
#42000
0#
01
#43000
1#
11
b11 I
b10 O
#44000
0#
01
#45000
1#
11
b0 I
b100 H
b11 O
#46000
0#
01
#47000
1#
11
b1 I
b0 O
b100 N
#48000
0#
01
#49000
1#
11
b10 I
b1 O
#50000
0#
01
#51000
1#
11
b11 I
b10 O
#52000
0#
01
#53000
1#
11
b0 I
b101 H
b11 O
#54000
0#
01
#55000
1#
11
b1 I
b0 O
b101 N
#56000
0#
01
#57000
1#
11
b10 I
b1 O
#58000
0#
01
#59000
1#
11
b11 I
b10 O
#60000
0#
01
#61000
1#
11
b0 I
b110 H
b11 O
#62000
0#
01
#63000
1#
11
b1 I
b0 O
b110 N
#64000
0#
01
#65000
1#
11
b10 I
b1 O
#66000
0#
01
#67000
1#
11
b11 I
b10 O
#68000
0#
01
#69000
1#
11
b0 I
b111 H
b11 O
#70000
0#
01
#71000
1#
11
b1 I
b0 O
b111 N
#72000
0#
01
#73000
1#
11
b10 I
b1 O
#74000
0#
01
#75000
1#
11
b11 I
b10 O
#76000
0#
01
#77000
1#
11
b0 I
b11 F
b11 O
#78000
0#
01
#79000
1#
11
1D
b1 I
b0 O
b11 M
b0 N
13
1)
16
#80000
0#
01
#81000
1#
11
b10 I
1Q
b1 O
#82000
0#
01
#83000
1#
11
b11 I
b10 O
#84000
0#
01
#85000
1#
11
b0 F
b0 I
b11 O
0E
04
0&
#86000
0#
01
#87000
1#
11
1K
b0 M
b0 O
17
1'
#88000
0#
01
#89000
1#
11
#90000
0#
01
#91000
1#
11
#92000
0#
01
#93000
1#
11
#94000
0#
01
#95000
1#
11
#96000
0#
01
#97000
1#
11
0$
02
b0 H
b0 G
b0 P
0K
07
b0 L
b0 :
0'
b0 8
b0 (
#98000
0#
01
#99000
1#
11
1$
b10 "
0%
0/
1.
00
b10 9
0C
1B
12
#100000
0#
01
#101000
1#
11
1%
b1 F
b10 G
1E
10
14
1&
#102000
0#
01
#103000
1#
11
0D
b1 I
03
0)
06
#104000
0#
01
#105000
1#
11
b10 I
0Q
#106000
0#
01
#107000
1#
11
b11 I
b1 M
#108000
0#
01
#109000
1#
11
b10 F
b0 I
b1 O
#110000
0#
01
#111000
1#
11
b1 I
b10 M
b0 O
#112000
0#
01
#113000
1#
11
b10 I
b1 O
#114000
0#
01
#115000
1#
11
b11 I
b10 O
#116000
0#
01
#117000
1#
11
b0 I
b1 H
b11 O
#118000
0#
01
#119000
1#
11
1D
b1 I
b0 O
b1 N
13
1)
16
#120000
0#
01
#121000
1#
11
b10 I
1Q
b1 O
#122000
0#
01
#123000
1#
11
b11 I
b10 O
#124000
0#
01
#125000
1#
11
b0 I
b10 H
b11 O
#126000
0#
01
#127000
1#
11
0D
b1 I
b0 O
b10 P
b10 N
b10 L
03
0)
b10 :
b10 8
06
b10 (
#128000
0#
01
#129000
1#
11
b10 I
0Q
b1 O
#130000
0#
01
#131000
1#
11
b11 I
b10 O
#132000
0#
01
#133000
1#
11
b0 I
b11 H
b11 O
#134000
0#
01
#135000
1#
11
b1 I
b0 O
b11 N
#136000
0#
01
#137000
1#
11
b10 I
b1 O
#138000
0#
01
#139000
1#
11
b11 I
b10 O
#140000
0#
01
#141000
1#
11
b0 I
b100 H
b11 O
#142000
0#
01
#143000
1#
11
b1 I
b0 O
b100 N
#144000
0#
01
#145000
1#
11
b10 I
b1 O
#146000
0#
01
#147000
1#
11
b11 I
b10 O
#148000
0#
01
#149000
1#
11
b0 I
b101 H
b11 O
#150000
0#
01
#151000
1#
11
b1 I
b0 O
b101 N
#152000
0#
01
#153000
1#
11
b10 I
b1 O
#154000
0#
01
#155000
1#
11
b11 I
b10 O
#156000
0#
01
#157000
1#
11
b0 I
b110 H
b11 O
#158000
0#
01
#159000
1#
11
b1 I
b0 O
b110 N
#160000
0#
01
#161000
1#
11
b10 I
b1 O
#162000
0#
01
#163000
1#
11
b11 I
b10 O
#164000
0#
01
#165000
1#
11
b0 I
b111 H
b11 O
#166000
0#
01
#167000
1#
11
b1 I
b0 O
b111 N
#168000
0#
01
#169000
1#
11
b10 I
b1 O
#170000
0#
01
#171000
1#
11
b11 I
b10 O
#172000
0#
01
#173000
1#
11
b0 I
b11 F
b11 O
#174000
0#
01
#175000
1#
11
1D
b1 I
b0 O
b11 M
b0 N
13
1)
16
#176000
0#
01
#177000
1#
11
b10 I
1Q
b1 O
#178000
0#
01
#179000
1#
11
b11 I
b10 O
#180000
0#
01
#181000
1#
11
b0 F
b0 I
b11 O
0E
04
0&
#182000
0#
01
#183000
1#
11
1K
b0 M
b0 O
17
1'
#184000
0#
01
#185000
1#
11
#186000
0#
01
#187000
1#
11
#188000
0#
01
#189000
1#
11
#190000
0#
01
#191000
1#
11
#192000
0#
01
#193000
1#
11
0$
02
b0 H
b0 G
b0 P
0K
07
b0 L
b0 :
0'
b0 8
b0 (
#194000
0#
01
#195000
1#
11
1$
b11 "
0%
1/
00
b11 9
1C
12
#196000
0#
01
#197000
1#
11
1%
b1 F
b11 G
1E
10
14
1&
#198000
0#
01
#199000
1#
11
0D
b1 I
03
0)
06
#200000
0#
01
#201000
1#
11
b10 I
0Q
#202000
0#
01
#203000
1#
11
b11 I
b1 M
#204000
0#
01
#205000
1#
11
b10 F
b0 I
b1 O
#206000
0#
01
#207000
1#
11
1D
b1 I
b10 M
b0 O
13
1)
16
#208000
0#
01
#209000
1#
11
b10 I
1Q
b1 O
#210000
0#
01
#211000
1#
11
b11 I
b10 O
#212000
0#
01
#213000
1#
11
b0 I
b1 H
b11 O
#214000
0#
01
#215000
1#
11
b1 I
b0 O
b1 P
b1 N
b1 L
b1 :
b1 8
b1 (
#216000
0#
01
#217000
1#
11
b10 I
b1 O
#218000
0#
01
#219000
1#
11
b11 I
b10 O
#220000
0#
01
#221000
1#
11
b0 I
b10 H
b11 O
#222000
0#
01
#223000
1#
11
0D
b1 I
b0 O
b11 P
b10 N
b11 L
03
0)
b11 :
b11 8
06
b11 (
#224000
0#
01
#225000
1#
11
b10 I
0Q
b1 O
#226000
0#
01
#227000
1#
11
b11 I
b10 O
#228000
0#
01
#229000
1#
11
b0 I
b11 H
b11 O
#230000
0#
01
#231000
1#
11
b1 I
b0 O
b11 N
#232000
0#
01
#233000
1#
11
b10 I
b1 O
#234000
0#
01
#235000
1#
11
b11 I
b10 O
#236000
0#
01
#237000
1#
11
b0 I
b100 H
b11 O
#238000
0#
01
#239000
1#
11
b1 I
b0 O
b100 N
#240000
0#
01
#241000
1#
11
b10 I
b1 O
#242000
0#
01
#243000
1#
11
b11 I
b10 O
#244000
0#
01
#245000
1#
11
b0 I
b101 H
b11 O
#246000
0#
01
#247000
1#
11
b1 I
b0 O
b101 N
#248000
0#
01
#249000
1#
11
b10 I
b1 O
#250000
0#
01
#251000
1#
11
b11 I
b10 O
#252000
0#
01
#253000
1#
11
b0 I
b110 H
b11 O
#254000
0#
01
#255000
1#
11
b1 I
b0 O
b110 N
#256000
0#
01
#257000
1#
11
b10 I
b1 O
#258000
0#
01
#259000
1#
11
b11 I
b10 O
#260000
0#
01
#261000
1#
11
b0 I
b111 H
b11 O
#262000
0#
01
#263000
1#
11
b1 I
b0 O
b111 N
#264000
0#
01
#265000
1#
11
b10 I
b1 O
#266000
0#
01
#267000
1#
11
b11 I
b10 O
#268000
0#
01
#269000
1#
11
b0 I
b11 F
b11 O
#270000
0#
01
#271000
1#
11
1D
b1 I
b0 O
b11 M
b0 N
13
1)
16
#272000
0#
01
#273000
1#
11
b10 I
1Q
b1 O
#274000
0#
01
#275000
1#
11
b11 I
b10 O
#276000
0#
01
#277000
1#
11
b0 F
b0 I
b11 O
0E
04
0&
#278000
0#
01
#279000
1#
11
1K
b0 M
b0 O
17
1'
#280000
0#
01
#281000
1#
11
#282000
0#
01
#283000
1#
11
#284000
0#
01
#285000
1#
11
#286000
0#
01
#287000
1#
11
#288000
0#
01
#289000
1#
11
0$
02
b0 H
b0 G
b0 P
0K
07
b0 L
b0 :
0'
b0 8
b0 (
#290000
0#
01
#291000
1#
11
1$
b100 "
0%
0/
0.
1-
00
b100 9
0C
0B
1A
12
#292000
0#
01
#293000
1#
11
1%
b1 F
b100 G
1E
10
14
1&
#294000
0#
01
#295000
1#
11
0D
b1 I
03
0)
06
#296000
0#
01
#297000
1#
11
b10 I
0Q
#298000
0#
01
#299000
1#
11
b11 I
b1 M
#300000
0#
01
#301000
1#
11
b10 F
b0 I
b1 O
#302000
0#
01
#303000
1#
11
b1 I
b10 M
b0 O
#304000
0#
01
#305000
1#
11
b10 I
b1 O
#306000
0#
01
#307000
1#
11
b11 I
b10 O
#308000
0#
01
#309000
1#
11
b0 I
b1 H
b11 O
#310000
0#
01
#311000
1#
11
b1 I
b0 O
b1 N
#312000
0#
01
#313000
1#
11
b10 I
b1 O
#314000
0#
01
#315000
1#
11
b11 I
b10 O
#316000
0#
01
#317000
1#
11
b0 I
b10 H
b11 O
#318000
0#
01
#319000
1#
11
1D
b1 I
b0 O
b10 N
13
1)
16
#320000
0#
01
#321000
1#
11
b10 I
1Q
b1 O
#322000
0#
01
#323000
1#
11
b11 I
b10 O
#324000
0#
01
#325000
1#
11
b0 I
b11 H
b11 O
#326000
0#
01
#327000
1#
11
0D
b1 I
b0 O
b100 P
b11 N
b100 L
03
0)
b100 :
b100 8
06
b100 (
#328000
0#
01
#329000
1#
11
b10 I
0Q
b1 O
#330000
0#
01
#331000
1#
11
b11 I
b10 O
#332000
0#
01
#333000
1#
11
b0 I
b100 H
b11 O
#334000
0#
01
#335000
1#
11
b1 I
b0 O
b100 N
#336000
0#
01
#337000
1#
11
b10 I
b1 O
#338000
0#
01
#339000
1#
11
b11 I
b10 O
#340000
0#
01
#341000
1#
11
b0 I
b101 H
b11 O
#342000
0#
01
#343000
1#
11
b1 I
b0 O
b101 N
#344000
0#
01
#345000
1#
11
b10 I
b1 O
#346000
0#
01
#347000
1#
11
b11 I
b10 O
#348000
0#
01
#349000
1#
11
b0 I
b110 H
b11 O
#350000
0#
01
#351000
1#
11
b1 I
b0 O
b110 N
#352000
0#
01
#353000
1#
11
b10 I
b1 O
#354000
0#
01
#355000
1#
11
b11 I
b10 O
#356000
0#
01
#357000
1#
11
b0 I
b111 H
b11 O
#358000
0#
01
#359000
1#
11
b1 I
b0 O
b111 N
#360000
0#
01
#361000
1#
11
b10 I
b1 O
#362000
0#
01
#363000
1#
11
b11 I
b10 O
#364000
0#
01
#365000
1#
11
b0 I
b11 F
b11 O
#366000
0#
01
#367000
1#
11
1D
b1 I
b0 O
b11 M
b0 N
13
1)
16
#368000
0#
01
#369000
1#
11
b10 I
1Q
b1 O
#370000
0#
01
#371000
1#
11
b11 I
b10 O
#372000
0#
01
#373000
1#
11
b0 F
b0 I
b11 O
0E
04
0&
#374000
0#
01
#375000
1#
11
1K
b0 M
b0 O
17
1'
#376000
0#
01
#377000
1#
11
#378000
0#
01
#379000
1#
11
#380000
0#
01
#381000
1#
11
#382000
0#
01
#383000
1#
11
#384000
0#
01
#385000
1#
11
0$
02
b0 H
b0 G
b0 P
0K
07
b0 L
b0 :
0'
b0 8
b0 (
#386000
0#
01
#387000
1#
11
1$
b101 "
0%
1/
00
b101 9
1C
12
#388000
0#
01
#389000
1#
11
1%
b1 F
b101 G
1E
10
14
1&
#390000
0#
01
#391000
1#
11
0D
b1 I
03
0)
06
#392000
0#
01
#393000
1#
11
b10 I
0Q
#394000
0#
01
#395000
1#
11
b11 I
b1 M
#396000
0#
01
#397000
1#
11
b10 F
b0 I
b1 O
#398000
0#
01
#399000
1#
11
1D
b1 I
b10 M
b0 O
13
1)
16
#400000
0#
01
#401000
1#
11
b10 I
1Q
b1 O
#402000
0#
01
#403000
1#
11
b11 I
b10 O
#404000
0#
01
#405000
1#
11
b0 I
b1 H
b11 O
#406000
0#
01
#407000
1#
11
0D
b1 I
b0 O
b1 P
b1 N
b1 L
03
0)
b1 :
b1 8
06
b1 (
#408000
0#
01
#409000
1#
11
b10 I
0Q
b1 O
#410000
0#
01
#411000
1#
11
b11 I
b10 O
#412000
0#
01
#413000
1#
11
b0 I
b10 H
b11 O
#414000
0#
01
#415000
1#
11
1D
b1 I
b0 O
b10 N
13
1)
16
#416000
0#
01
#417000
1#
11
b10 I
1Q
b1 O
#418000
0#
01
#419000
1#
11
b11 I
b10 O
#420000
0#
01
#421000
1#
11
b0 I
b11 H
b11 O
#422000
0#
01
#423000
1#
11
0D
b1 I
b0 O
b101 P
b11 N
b101 L
03
0)
b101 :
b101 8
06
b101 (
#424000
0#
01
#425000
1#
11
b10 I
0Q
b1 O
#426000
0#
01
#427000
1#
11
b11 I
b10 O
#428000
0#
01
#429000
1#
11
b0 I
b100 H
b11 O
#430000
0#
01
#431000
1#
11
b1 I
b0 O
b100 N
#432000
0#
01
#433000
1#
11
b10 I
b1 O
#434000
0#
01
#435000
1#
11
b11 I
b10 O
#436000
0#
01
#437000
1#
11
b0 I
b101 H
b11 O
#438000
0#
01
#439000
1#
11
b1 I
b0 O
b101 N
#440000
0#
01
#441000
1#
11
b10 I
b1 O
#442000
0#
01
#443000
1#
11
b11 I
b10 O
#444000
0#
01
#445000
1#
11
b0 I
b110 H
b11 O
#446000
0#
01
#447000
1#
11
b1 I
b0 O
b110 N
#448000
0#
01
#449000
1#
11
b10 I
b1 O
#450000
0#
01
#451000
1#
11
b11 I
b10 O
#452000
0#
01
#453000
1#
11
b0 I
b111 H
b11 O
#454000
0#
01
#455000
1#
11
b1 I
b0 O
b111 N
#456000
0#
01
#457000
1#
11
b10 I
b1 O
#458000
0#
01
#459000
1#
11
b11 I
b10 O
#460000
0#
01
#461000
1#
11
b0 I
b11 F
b11 O
#462000
0#
01
#463000
1#
11
1D
b1 I
b0 O
b11 M
b0 N
13
1)
16
#464000
0#
01
#465000
1#
11
b10 I
1Q
b1 O
#466000
0#
01
#467000
1#
11
b11 I
b10 O
#468000
0#
01
#469000
1#
11
b0 F
b0 I
b11 O
0E
04
0&
#470000
0#
01
#471000
1#
11
1K
b0 M
b0 O
17
1'
#472000
0#
01
#473000
1#
11
#474000
0#
01
#475000
1#
11
#476000
0#
01
#477000
1#
11
#478000
0#
01
#479000
1#
11
#480000
0#
01
#481000
1#
11
0$
02
b0 H
b0 G
b0 P
0K
07
b0 L
b0 :
0'
b0 8
b0 (
#482000
0#
01
#483000
1#
11
1$
b110 "
0%
0/
1.
00
b110 9
0C
1B
12
#484000
0#
01
#485000
1#
11
1%
b1 F
b110 G
1E
10
14
1&
#486000
0#
01
#487000
1#
11
0D
b1 I
03
0)
06
#488000
0#
01
#489000
1#
11
b10 I
0Q
#490000
0#
01
#491000
1#
11
b11 I
b1 M
#492000
0#
01
#493000
1#
11
b10 F
b0 I
b1 O
#494000
0#
01
#495000
1#
11
b1 I
b10 M
b0 O
#496000
0#
01
#497000
1#
11
b10 I
b1 O
#498000
0#
01
#499000
1#
11
b11 I
b10 O
#500000
0#
01
#501000
1#
11
b0 I
b1 H
b11 O
#502000
0#
01
#503000
1#
11
1D
b1 I
b0 O
b1 N
13
1)
16
#504000
0#
01
#505000
1#
11
b10 I
1Q
b1 O
#506000
0#
01
#507000
1#
11
b11 I
b10 O
#508000
0#
01
#509000
1#
11
b0 I
b10 H
b11 O
#510000
0#
01
#511000
1#
11
b1 I
b0 O
b10 P
b10 N
b10 L
b10 :
b10 8
b10 (
#512000
0#
01
#513000
1#
11
b10 I
b1 O
#514000
0#
01
#515000
1#
11
b11 I
b10 O
#516000
0#
01
#517000
1#
11
b0 I
b11 H
b11 O
#518000
0#
01
#519000
1#
11
0D
b1 I
b0 O
b110 P
b11 N
b110 L
03
0)
b110 :
b110 8
06
b110 (
#520000
0#
01
#521000
1#
11
b10 I
0Q
b1 O
#522000
0#
01
#523000
1#
11
b11 I
b10 O
#524000
0#
01
#525000
1#
11
b0 I
b100 H
b11 O
#526000
0#
01
#527000
1#
11
b1 I
b0 O
b100 N
#528000
0#
01
#529000
1#
11
b10 I
b1 O
#530000
0#
01
#531000
1#
11
b11 I
b10 O
#532000
0#
01
#533000
1#
11
b0 I
b101 H
b11 O
#534000
0#
01
#535000
1#
11
b1 I
b0 O
b101 N
#536000
0#
01
#537000
1#
11
b10 I
b1 O
#538000
0#
01
#539000
1#
11
b11 I
b10 O
#540000
0#
01
#541000
1#
11
b0 I
b110 H
b11 O
#542000
0#
01
#543000
1#
11
b1 I
b0 O
b110 N
#544000
0#
01
#545000
1#
11
b10 I
b1 O
#546000
0#
01
#547000
1#
11
b11 I
b10 O
#548000
0#
01
#549000
1#
11
b0 I
b111 H
b11 O
#550000
0#
01
#551000
1#
11
b1 I
b0 O
b111 N
#552000
0#
01
#553000
1#
11
b10 I
b1 O
#554000
0#
01
#555000
1#
11
b11 I
b10 O
#556000
0#
01
#557000
1#
11
b0 I
b11 F
b11 O
#558000
0#
01
#559000
1#
11
1D
b1 I
b0 O
b11 M
b0 N
13
1)
16
#560000
0#
01
#561000
1#
11
b10 I
1Q
b1 O
#562000
0#
01
#563000
1#
11
b11 I
b10 O
#564000
0#
01
#565000
1#
11
b0 F
b0 I
b11 O
0E
04
0&
#566000
0#
01
#567000
1#
11
1K
b0 M
b0 O
17
1'
#568000
0#
01
#569000
1#
11
#570000
0#
01
#571000
1#
11
#572000
0#
01
#573000
1#
11
#574000
0#
01
#575000
1#
11
#576000
0#
01
#577000
1#
11
0$
02
b0 H
b0 G
b0 P
0K
07
b0 L
b0 :
0'
b0 8
b0 (
#578000
0#
01
#579000
1#
11
1$
b111 "
0%
1/
00
b111 9
1C
12
#580000
0#
01
#581000
1#
11
1%
b1 F
b111 G
1E
10
14
1&
#582000
0#
01
#583000
1#
11
0D
b1 I
03
0)
06
#584000
0#
01
#585000
1#
11
b10 I
0Q
#586000
0#
01
#587000
1#
11
b11 I
b1 M
#588000
0#
01
#589000
1#
11
b10 F
b0 I
b1 O
#590000
0#
01
#591000
1#
11
1D
b1 I
b10 M
b0 O
13
1)
16
#592000
0#
01
#593000
1#
11
b10 I
1Q
b1 O
#594000
0#
01
#595000
1#
11
b11 I
b10 O
#596000
0#
01
#597000
1#
11
b0 I
b1 H
b11 O
#598000
0#
01
#599000
1#
11
b1 I
b0 O
b1 P
b1 N
b1 L
b1 :
b1 8
b1 (
#600000
0#
01
#601000
1#
11
b10 I
b1 O
#602000
0#
01
#603000
1#
11
b11 I
b10 O
#604000
0#
01
#605000
1#
11
b0 I
b10 H
b11 O
#606000
0#
01
#607000
1#
11
b1 I
b0 O
b11 P
b10 N
b11 L
b11 :
b11 8
b11 (
#608000
0#
01
#609000
1#
11
b10 I
b1 O
#610000
0#
01
#611000
1#
11
b11 I
b10 O
#612000
0#
01
#613000
1#
11
b0 I
b11 H
b11 O
#614000
0#
01
#615000
1#
11
0D
b1 I
b0 O
b111 P
b11 N
b111 L
03
0)
b111 :
b111 8
06
b111 (
#616000
0#
01
#617000
1#
11
b10 I
0Q
b1 O
#618000
0#
01
#619000
1#
11
b11 I
b10 O
#620000
0#
01
#621000
1#
11
b0 I
b100 H
b11 O
#622000
0#
01
#623000
1#
11
b1 I
b0 O
b100 N
#624000
0#
01
#625000
1#
11
b10 I
b1 O
#626000
0#
01
#627000
1#
11
b11 I
b10 O
#628000
0#
01
#629000
1#
11
b0 I
b101 H
b11 O
#630000
0#
01
#631000
1#
11
b1 I
b0 O
b101 N
#632000
0#
01
#633000
1#
11
b10 I
b1 O
#634000
0#
01
#635000
1#
11
b11 I
b10 O
#636000
0#
01
#637000
1#
11
b0 I
b110 H
b11 O
#638000
0#
01
#639000
1#
11
b1 I
b0 O
b110 N
#640000
0#
01
#641000
1#
11
b10 I
b1 O
#642000
0#
01
#643000
1#
11
b11 I
b10 O
#644000
0#
01
#645000
1#
11
b0 I
b111 H
b11 O
#646000
0#
01
#647000
1#
11
b1 I
b0 O
b111 N
#648000
0#
01
#649000
1#
11
b10 I
b1 O
#650000
0#
01
#651000
1#
11
b11 I
b10 O
#652000
0#
01
#653000
1#
11
b0 I
b11 F
b11 O
#654000
0#
01
#655000
1#
11
1D
b1 I
b0 O
b11 M
b0 N
13
1)
16
#656000
0#
01
#657000
1#
11
b10 I
1Q
b1 O
#658000
0#
01
#659000
1#
11
b11 I
b10 O
#660000
0#
01
#661000
1#
11
b0 F
b0 I
b11 O
0E
04
0&
